chroniq/__init__.py
chroniq/__main__.py
chroniq/audit.py
chroniq/changelog.py
chroniq/cli.py
chroniq/config.py
chroniq/core.py
chroniq/dcli.py
chroniq/logger.py
chroniq/rollback.py
chroniq/utils.py
chroniq-0.8.0.dist-info/entry_points.txt
chroniq-0.8.0.dist-info/METADATA
chroniq-0.8.0.dist-info/WHEEL
chroniq-0.8.0.dist-info/RECORD
