Metadata-Version: 2.3
Name: chroniq
Version: 0.8.0
Summary: A beginner-friendly, pro-grade versioning and changelog manager using SemVer and Markdown.
License: MIT
Keywords: versioning,changelog,semver,cli,developer-tools
Author: Brandon McKinney
Author-email: brandonmckinney2001@gmail.com
Requires-Python: >=3.11
Classifier: Environment :: Console
Classifier: License :: OSI Approved :: MIT License
Classifier: Operating System :: OS Independent
Classifier: Programming Language :: Python :: 3
Classifier: Programming Language :: Python :: 3.11
Classifier: Programming Language :: Python :: 3.12
Classifier: Programming Language :: Python :: 3.13
Classifier: Topic :: Software Development :: Version Control
Requires-Dist: click (>=8.1.7,<9.0.0)
Requires-Dist: rich (>=13.7.0,<14.0.0)
Project-URL: Homepage, https://github.com/BrandonAustin01/chroniq
Project-URL: Repository, https://github.com/BrandonAustin01/chroniq
